tutuka_client/__init__.py
tutuka_client/base.py
tutuka_client/client.py
tutuka_client/errors.py
tutuka_client/response_codes.py
tutuka_client/stop_reasons.py
tutuka_client/utils/__init__.py
tutuka_client/utils/datetime_iso8601.py
tutuka_client/utils/hash_content.py
tutuka_client/utils/normalize_argument.py
python_tutuka_client_testing-1.3.0.dist-info/LICENSE
python_tutuka_client_testing-1.3.0.dist-info/METADATA
python_tutuka_client_testing-1.3.0.dist-info/WHEEL
python_tutuka_client_testing-1.3.0.dist-info/top_level.txt
python_tutuka_client_testing-1.3.0.dist-info/RECORD
