Metadata-Version: 2.1
Name: python-tutuka-client-testing
Version: 1.3.0
Summary: Tutuka XML-RPC Client
Home-page: https://github.com/Fondeadora/tutuka-client
Author: Fondeadora
Author-email: tech@fondeadora.com
Keywords: tutuka,client
Classifier: Programming Language :: Python :: 3.6
Classifier: Programming Language :: Python :: 3.7
Classifier: Programming Language :: Python :: 3.8
Classifier: License :: OSI Approved :: MIT License
Classifier: Operating System :: OS Independent
Requires-Python: >=3.6
License-File: LICENSE
Requires-Dist: requests (>=2.24.0)
Requires-Dist: cryptography (>=2.9.2)
